LICENSE
README.md
setup.py
grafana_backup/__init__.py
grafana_backup/api_checks.py
grafana_backup/archive.py
grafana_backup/azure_storage_download.py
grafana_backup/azure_storage_upload.py
grafana_backup/cli.py
grafana_backup/commons.py
grafana_backup/constants.py
grafana_backup/create_alert_channel.py
grafana_backup/create_annotation.py
grafana_backup/create_dashboard.py
grafana_backup/create_datasource.py
grafana_backup/create_folder.py
grafana_backup/create_org.py
grafana_backup/create_snapshot.py
grafana_backup/create_user.py
grafana_backup/dashboardApi.py
grafana_backup/delete.py
grafana_backup/delete_alert_channels.py
grafana_backup/delete_annotations.py
grafana_backup/delete_dashboards.py
grafana_backup/delete_datasources.py
grafana_backup/delete_folders.py
grafana_backup/delete_snapshots.py
grafana_backup/gcs_download.py
grafana_backup/gcs_upload.py
grafana_backup/grafanaSettings.py
grafana_backup/make_users_viewers.py
grafana_backup/pause_alerts.py
grafana_backup/restore.py
grafana_backup/restore_user_permissions.py
grafana_backup/s3_download.py
grafana_backup/s3_upload.py
grafana_backup/save.py
grafana_backup/save_alert_channels.py
grafana_backup/save_annotations.py
grafana_backup/save_dashboards.py
grafana_backup/save_datasources.py
grafana_backup/save_folders.py
grafana_backup/save_orgs.py
grafana_backup/save_snapshots.py
grafana_backup/save_users.py
grafana_backup/save_versions.py
grafana_backup/tools.py
grafana_backup/unpause_alerts.py
grafana_backup/update_folder_permissions.py
grafana_backup/conf/grafanaSettings.json
managed_grafana_backup.egg-info/PKG-INFO
managed_grafana_backup.egg-info/SOURCES.txt
managed_grafana_backup.egg-info/dependency_links.txt
managed_grafana_backup.egg-info/entry_points.txt
managed_grafana_backup.egg-info/requires.txt
managed_grafana_backup.egg-info/top_level.txt