Metadata-Version: 2.1
Name: managed-grafana-backup
Version: 1.2.4
Summary: A Python-based application to backup Grafana settings using the Grafana API
Home-page: https://github.com/ysde/grafana-backup-tool
Author: author
Author-email: ysde108@gmail.com
License: UNKNOWN
Platform: UNKNOWN
